<?xml version="1.0"?>
<!DOCTYPE liferay-portlet-app PUBLIC "-//Liferay//DTD Portlet Application 6.2.0//EN" "http://www.liferay.com/dtd/liferay-portlet-app_6_2_0.dtd">

<liferay-portlet-app>
	<portlet>
		<portlet-name>WorkPlanManagement</portlet-name>
		<icon>/icon.png</icon>
		<requires-namespaced-parameters>false</requires-namespaced-parameters>
		<header-portal-css>/html/js/aui/cssgrids/cssgrids-min.css</header-portal-css>
		<header-portlet-css>/css/main.css</header-portlet-css>
		<footer-portlet-javascript>/js/BaseTableWidget.js</footer-portlet-javascript>
		<footer-portlet-javascript>/js/WorkplanNodeDomHelper.js</footer-portlet-javascript>
		<footer-portlet-javascript>/js/PublishedWorkPlanNodeTableWidget.js</footer-portlet-javascript>
		<footer-portlet-javascript>/js/MyWorkPlanNodeTableWidget.js</footer-portlet-javascript>
		<footer-portlet-javascript>/js/RecordAdding.js</footer-portlet-javascript>
		<css-class-wrapper>WorkPlanManagement-portlet</css-class-wrapper>
	</portlet>
	<portlet>
		<portlet-name>ResearchAchievemet</portlet-name>
		<icon>/icon.png</icon>
		<requires-namespaced-parameters>false</requires-namespaced-parameters>
		<header-portal-css>/html/js/aui/cssgrids/cssgrids-min.css</header-portal-css>
		<header-portlet-css>/css/main.css</header-portlet-css>
		<footer-portlet-javascript>/js/BaseTableWidget.js</footer-portlet-javascript>
		<footer-portlet-javascript>/js/WorkplanNodeDomHelper.js</footer-portlet-javascript>
		<footer-portlet-javascript>/js/PublishedWorkPlanNodeTableWidget.js</footer-portlet-javascript>
		<footer-portlet-javascript>/js/MyWorkPlanNodeTableWidget.js</footer-portlet-javascript>
		<footer-portlet-javascript>/js/RecordAdding.js</footer-portlet-javascript>
		<css-class-wrapper>ResearchAchievemet-portlet</css-class-wrapper>
	</portlet>
	<portlet>
		<portlet-name>WorkflowManagement</portlet-name>
		<icon>/icon.png</icon>
		<requires-namespaced-parameters>false</requires-namespaced-parameters>
		<header-portlet-css>/css/main.css</header-portlet-css>
		<footer-portlet-javascript>/js/BaseTableWidget.js</footer-portlet-javascript>
		<footer-portlet-javascript>/js/WorkplanNodeDomHelper.js</footer-portlet-javascript>
		<footer-portlet-javascript>/js/WorkflowNodeTableWidget.js</footer-portlet-javascript>
		<css-class-wrapper>WorkflowManagement-portlet</css-class-wrapper>
	</portlet>
	<role-mapper>
		<role-name>administrator</role-name>
		<role-link>Administrator</role-link>
	</role-mapper>
	<role-mapper>
		<role-name>guest</role-name>
		<role-link>Guest</role-link>
	</role-mapper>
	<role-mapper>
		<role-name>power-user</role-name>
		<role-link>Power User</role-link>
	</role-mapper>
	<role-mapper>
		<role-name>user</role-name>
		<role-link>User</role-link>
	</role-mapper>
</liferay-portlet-app>